README.md
setup.cfg
setup.py
lykkex/__init__.py
lykkex/lykkex.py
lykkex.egg-info/PKG-INFO
lykkex.egg-info/SOURCES.txt
lykkex.egg-info/dependency_links.txt
lykkex.egg-info/not-zip-safe
lykkex.egg-info/requires.txt
lykkex.egg-info/top_level.txt