Metadata-Version: 1.0
Name: lykkex
Version: 0.1
Summary: Wrapper for the Lykke Exchange API
Home-page: https://github.com/pfeffer90/lykkex
Author: Paul Pfeiffer, Stefan Voigt
Author-email: pfeifferpaul90@gmail.com
License: MIT
Platform: UNKNOWN
